scrolltext_gif/__init__.py
scrolltext_gif/__main__.py
scrolltext_gif/circle.py
scrolltext_gif/vertical.py
scrolltext_gif-0.9.5.dist-info/METADATA
scrolltext_gif-0.9.5.dist-info/WHEEL
scrolltext_gif-0.9.5.dist-info/RECORD
