Metadata-Version: 2.1
Name: scrolltext_gif
Version: 0.9.5
Summary: Module for generating gif-s with scrolling vertical text
License: MIT
Author: Artemii
Author-email: angap4@gmail.com
Requires-Python: >=3.10,<4.0
Classifier: License :: OSI Approved :: MIT License
Classifier: Programming Language :: Python :: 3
Classifier: Programming Language :: Python :: 3.10
Classifier: Programming Language :: Python :: 3.11
Classifier: Programming Language :: Python :: 3.12
Provides-Extra: docs
Requires-Dist: pillow (>=10.4.0,<11.0.0)
Requires-Dist: seaborn (>=0.13.2,<0.14.0)
Project-URL: repository, https://github.com/Jrol123/scrollTextProject
